wltp/__init__.py
wltp/__main__.py
wltp/_version.py
wltp/experiment.py
wltp/idgears.py
wltp/model.py
wltp/pandel.py
wltp/plots.py
wltp/utils.py
wltp/cycles/__init__.py
wltp/cycles/class1.py
wltp/cycles/class2.py
wltp/cycles/class3.py
wltp/cycles/nedc.py
wltp/excel/ExcelPython.ico
wltp/excel/WltpExcelRunner.py
wltp/excel/WltpExcelRunner.xlsm
wltp/excel/__init__.py
wltp/excel/pandalon.vba
wltp/excel/requirements.txt
wltp/excel/xlsutils.py
wltp/excel/xlwings_pandalon.vba
wltp-0.1.2a0.dist-info/LICENSE.txt
wltp-0.1.2a0.dist-info/METADATA
wltp-0.1.2a0.dist-info/WHEEL
wltp-0.1.2a0.dist-info/entry_points.txt
wltp-0.1.2a0.dist-info/top_level.txt
wltp-0.1.2a0.dist-info/zip-safe
wltp-0.1.2a0.dist-info/RECORD
