Metadata-Version: 2.1
Name: wltp
Version: 0.1.2a0
Summary: wltp: generate WLTC gear-shifts based on vehicle characteristics
Home-page: https://github.com/JRCSTU/wltp
Author: JRC-SRU on behalf of UNECE's GearShifting TF
Author-email: ankostis@gmail.com
License: European Union Public Licence 1.1 or later (EUPL 1.1+)
Download-URL: https://github.com/ankostis/wltp/tarball/v0.1.2a0
Project-URL: Documentation, https://wltp.readthedocs.io/
Project-URL: Sources, https://github.com/JRCSTU/wltp
Project-URL: Bug Tracker, https://github.com/JRCSTU/wltp/issues
Keywords: automotive,vehicles,Light-Duty-Vehicles,cars,gears,gearshifs,simulator,driving,engine,WLTP,wltc,UNECE,standards
Platform: UNKNOWN
Classifier: Programming Language :: Python
Classifier: Programming Language :: Python :: 2
Classifier: Programming Language :: Python :: 2.7
Classifier: Programming Language :: Python :: 3
Classifier: Programming Language :: Python :: 3.3
Classifier: Programming Language :: Python :: 3.4
Classifier: Programming Language :: Python :: 3.5
Classifier: Programming Language :: Python :: 3.6
Classifier: Programming Language :: Python :: 3.7
Classifier: Programming Language :: Python :: Implementation :: CPython
Classifier: Development Status :: 3 - Alpha
Classifier: Natural Language :: English
Classifier: Intended Audience :: Developers
Classifier: Intended Audience :: Science/Research
Classifier: Intended Audience :: Manufacturing
Classifier: License :: OSI Approved :: European Union Public Licence 1.1 (EUPL 1.1)
Classifier: Operating System :: MacOS :: MacOS X
Classifier: Operating System :: Microsoft :: Windows
Classifier: Operating System :: POSIX
Classifier: Operating System :: OS Independent
Classifier: Topic :: Scientific/Engineering
Classifier: Topic :: Software Development :: Libraries :: Python Modules
Requires-Dist: six
Requires-Dist: jsonschema (<3,>=2.5)
Requires-Dist: numpy
Requires-Dist: pandas
Requires-Dist: mock ; python_version == "2.7"
Provides-Extra: dev
Requires-Dist: nose ; extra == 'dev'
Requires-Dist: coverage ; extra == 'dev'
Requires-Dist: matplotlib ; extra == 'dev'
Requires-Dist: coveralls ; extra == 'dev'
Requires-Dist: docopt ; extra == 'dev'
Requires-Dist: sphinx (>=1.2) ; extra == 'dev'
Requires-Dist: wheel ; extra == 'dev'
Requires-Dist: twine ; extra == 'dev'
Requires-Dist: pylint ; extra == 'dev'
Requires-Dist: black ; extra == 'dev'
Requires-Dist: doc8 ; extra == 'dev'
Requires-Dist: sphinx-autobuild ; extra == 'dev'
Requires-Dist: xlwings ; (sys_platform == "win32") and extra == 'dev'
Provides-Extra: excel
Requires-Dist: xlwings ; (sys_platform == "win32") and extra == 'excel'
Provides-Extra: plot
Requires-Dist: matplotlib ; extra == 'plot'
